{
  "posTrigrams": {
    "NNP,NNP,NNS": 1,
    "IN,NNP,VBZ": 3,
    "DT,CD,JJ": 1,
    "NN,NN,TO": 1,
    "NNP,NNP,POS": 1,
    "CD,JJ,NN": 1,
    "CC,DT,CD": 1,
    "NNP,POS,NN": 1,
    "NNP,VBZ,IN": 2,
    "DT,NNP,NNP": 1,
    "NNP,VBZ,PRP$": 2,
    "NN,CC,PRP$": 1,
    "JJ,NNS,NNP": 1,
    "NNP,CC,NNP": 4,
    "NNP,VBZ,VBN": 2,
    "IN,DT,JJ": 3,
    "JJ,NN,WDT": 1,
    "VBZ,VBN,IN": 1,
    "PRP,VBZ,TO": 1,
    "VB,RB,IN": 1,
    "WRB,DT,NN": 2,
    "NNP,VBZ,TO": 2,
    "VB,DT,NN": 1,
    "IN,DT,NNS": 1,
    "NNP,CC,PRP$": 1,
    "NNS,VBP,VBN": 1,
    "IN,VBG,PRP$": 1,
    "PRP,VBP,DT": 1,
    "NN,IN,DT": 3,
    "RB,NNP,VBZ": 1,
    "NN,VBN,NNP": 2,
    "PRP,VBZ,PRP": 1,
    "TO,VB,IN": 1,
    "PRP,CC,NNP": 1,
    "VBZ,JJ,IN": 1,
    "PRP,VBZ,IN": 1,
    "DT,JJ,NN": 3,
    "IN,PRP,RB": 1,
    "VBZ,TO,PRP": 1,
    "VBG,IN,PRP": 1,
    "VBZ,VBG,IN": 1,
    "JJ,NNS,WDT": 1,
    "VBP,PRP,IN": 1,
    "DT,NN,VBZ": 3,
    "VBN,IN,DT": 2,
    "JJ,NN,CC": 1,
    "NN,TO,VB": 3,
    "NNP,VBZ,RB": 2,
    "RB,JJ,CC": 1,
    "NN,IN,NNP": 1,
    "PRP,VBZ,DT": 1,
    "RB,RB,RB": 1,
    "NNP,VBZ,NNP": 1,
    "VBG,PRP$,NN": 1,
    "DT,CD,VBN": 1,
    "NNS,IN,NNP": 1,
    "VBZ,IN,WRB": 1,
    "NNP,VBD,DT": 1,
    "IN,TO,VB": 1,
    "VB,IN,WRB": 1,
    "PRP,VBZ,VBN": 1,
    "TO,NNP,JJ": 1,
    "IN,PRP,VBZ": 1,
    "JJ,IN,PRP": 1,
    "PRP,VBZ,RB": 2,
    "JJ,CC,VBZ": 1,
    "TO,VB,PRP": 2,
    "VBN,IN,CD": 1,
    "IN,DT,NN": 6,
    "NNS,WDT,VBZ": 1,
    "TO,DT,NN": 1,
    "IN,NNP,NNP": 1,
    "IN,RB,DT": 1,
    "NN,RB,VBZ": 2,
    "CC,IN,DT": 2,
    "NN,RB,DT": 2,
    "DT,NN,NN": 1,
    "VBZ,DT,NN": 1,
    "CC,NNP,VBZ": 2,
    "JJ,IN,PRP$": 1,
    "NN,VBZ,JJ": 1,
    "CC,NNP,RB": 1,
    "VBZ,PRP,RB": 1,
    "TO,PRP$,NN": 1,
    "RB,VBZ,RB": 1,
    "VBN,RB,NNP": 1,
    "VBZ,IN,NN": 1,
    "VBZ,VBN,JJ": 1,
    "PRP,VBZ,RP": 1,
    "TO,VB,NNP": 1,
    "TO,VB,VBG": 1,
    "DT,NN,IN": 1,
    "PRP,VBD,TO": 1,
    "VB,RP,NNP": 1,
    "NNP,VBZ,JJ": 2,
    "CC,JJ,IN": 1,
    "NNP,VBD,RB": 1,
    "VBN,TO,VB": 1,
    "CC,VBN,PRP$": 1,
    "PRP,VBZ,PRP$": 1,
    "NNP,VBZ,RP": 1,
    "IN,NNP,WP": 1,
    "VBZ,IN,NNP": 1,
    "VBD,IN,DT": 1,
    "IN,NNP,CC": 2,
    "VBG,NNP,CC": 1,
    "VBZ,IN,PRP": 1,
    "VBD,DT,NN": 1,
    "WP,VBD,PRP": 1,
    "NNP,VBZ,DT": 1,
    "NN,CC,RB": 1,
    "IN,VBG,CD": 1,
    "VBN,CC,NNP": 1,
    "CC,DT,JJ": 1,
    "NNS,VBP,IN": 1,
    "JJ,NNS,IN": 1,
    "PRP,VBZ,NNP": 1,
    "WP$,NN,VBZ": 1,
    "VBN,CC,VBZ": 1,
    "RB,TO,VB": 1,
    "NN,NN,WDT": 1,
    "NNP,VBZ,VBG": 1,
    "NNS,IN,PRP$": 1,
    "VBP,IN,TO": 1,
    "VB,IN,DT": 1,
    "NN,CC,NNP": 1,
    "CC,PRP$,NNS": 1,
    "VBP,RB,IN": 1,
    "DT,NNS,VBP": 1,
    "VB,NNP,RB": 1,
    "TO,NNP,CC": 1,
    "NNP,RB,VBZ": 1,
    "VBZ,DT,JJ": 1,
    "NNP,WDT,NNP": 1,
    "VBZ,IN,IN": 1
  },
  "characterTrigrams": {
    "200": 1,
    "Bal": 6,
    "to ": 12,
    "III": 1,
    ": W": 1,
    "ing": 7,
    "s o": 1,
    "f C": 1,
    "han": 1,
    "ge ": 2,
    "is ": 10,
    "a 2": 1,
    "004": 1,
    " Am": 1,
    "eri": 3,
    "can": 1,
    " st": 2,
    "rai": 3,
    "ght": 1,
    "-to": 1,
    "-vi": 1,
    "deo": 1,
    " se": 2,
    "que": 1,
    "l t": 2,
    "o U": 1,
    "niv": 1,
    "ers": 1,
    "al ": 1,
    "Stu": 1,
    "dio": 1,
    "s' ": 1,
    "2 a": 1,
    "nim": 1,
    "ate": 1,
    "d f": 2,
    "ilm": 1,
    " \"\"": 1,
    ", a": 4,
    "nd ": 10,
    "the": 14,
    " 19": 1,
    "95 ": 1,
    "fil": 1,
    "m B": 1,
    "alt": 7,
    "o. ": 1,
    " Ba": 5,
    "lto": 6,
    "'s ": 4,
    "son": 2,
    " Ko": 2,
    "di ": 2,
    "wor": 1,
    "ks ": 3,
    "for": 4,
    " th": 17,
    "e U": 1,
    "S M": 1,
    "ail": 2,
    ". K": 2,
    "odi": 5,
    " lo": 2,
    "ves": 1,
    " hi": 4,
    "s j": 1,
    "ob ": 1,
    "and": 3,
    "s n": 1,
    "ew ": 1,
    "fri": 2,
    "end": 2,
    "s D": 2,
    "ust": 1,
    "y, ": 3,
    "Kir": 1,
    "by ": 2,
    " Ra": 1,
    "lph": 1,
    ". B": 4,
    "o i": 3,
    "s i": 5,
    "ntr": 1,
    "igu": 1,
    "ed ": 8,
    " ne": 2,
    "w b": 1,
    "ush": 2,
    " pl": 3,
    "ane": 3,
    "at ": 5,
    "has": 2,
    " ar": 2,
    "riv": 1,
    "in ": 2,
    "Nom": 1,
    "e. ": 5,
    "He ": 1,
    "wis": 1,
    "hes": 1,
    " to": 7,
    " fl": 2,
    "jus": 2,
    "t l": 1,
    "ike": 1,
    "e p": 4,
    "lan": 5,
    "Whe": 1,
    "n t": 3,
    "he ": 14,
    "pil": 2,
    "ot ": 3,
    "Duk": 3,
    "e o": 1,
    "ffe": 1,
    "rs ": 2,
    "tak": 1,
    "e t": 3,
    "pla": 3,
    "ce ": 2,
    "of ": 4,
    " ma": 2,
    "il-": 1,
    "dog": 2,
    "s, ": 1,
    "Kod": 3,
    "i a": 1,
    "his": 5,
    " fr": 3,
    "ien": 1,
    "ds ": 1,
    "are": 1,
    " wo": 1,
    "rri": 2,
    "abo": 2,
    "ut ": 5,
    "los": 1,
    "eir": 1,
    " jo": 2,
    "bs.": 1,
    " Th": 3,
    "ey ": 1,
    "hav": 1,
    "e a": 3,
    " re": 1,
    "sen": 1,
    "tme": 1,
    "nt ": 4,
    "aga": 1,
    "ins": 2,
    "t t": 3,
    "ot.": 1,
    " Me": 1,
    "anw": 1,
    "hil": 1,
    "e, ": 2,
    "Bor": 3,
    "fal": 1,
    "ls ": 1,
    " a ": 4,
    "fem": 1,
    "ale": 1,
    " go": 1,
    "ose": 2,
    " na": 1,
    "med": 1,
    " St": 2,
    "ell": 2,
    "a. ": 1,
    "She": 1,
    " as": 2,
    "him": 4,
    "y w": 2,
    "ith": 3,
    " he": 7,
    "r, ": 1,
    "but": 2,
    " Bo": 2,
    "ris": 2,
    " is": 8,
    " af": 1,
    "d o": 1,
    "f h": 1,
    "eig": 1,
    "hts": 1,
    ". H": 3,
    "e w": 1,
    "ait": 1,
    "s u": 1,
    "nti": 1,
    "las": 1,
    "t m": 1,
    "ome": 4,
    "bef": 1,
    "ore": 1,
    " ev": 2,
    "ent": 2,
    "ual": 2,
    "ly ": 3,
    "lie": 3,
    "s t": 6,
    "o h": 4,
    "er,": 1,
    " cl": 1,
    "aim": 1,
    "he'": 2,
    "s s": 1,
    "uff": 1,
    "ng ": 4,
    "fro": 1,
    "m n": 1,
    "ume": 1,
    "rou": 1,
    "nju": 1,
    "rie": 2,
    "hat": 2,
    " pr": 1,
    "eve": 1,
    "om ": 2,
    "fly": 1,
    ". A": 2,
    " ra": 1,
    "org": 1,
    "ani": 1,
    "sed": 2,
    " be": 5,
    "twe": 1,
    "en ": 1,
    " do": 2,
    "g-s": 1,
    "led": 1,
    " te": 1,
    "am ": 1,
    "e b": 2,
    " wa": 4,
    "nts": 1,
    "s f": 1,
    "ath": 1,
    "er ": 2,
    "lea": 1,
    "d h": 2,
    "tea": 2,
    "m. ": 1,
    "not": 2,
    " so": 1,
    " su": 3,
    "re,": 1,
    " bu": 3,
    "t a": 1,
    "fte": 3,
    "r a": 1,
    " li": 1,
    "ttl": 1,
    "e c": 2,
    "onv": 1,
    "inc": 1,
    "Jen": 1,
    "na,": 1,
    " ac": 1,
    "cep": 1,
    "ts ": 3,
    " of": 2,
    "fer": 1,
    ". N": 1,
    "lon": 1,
    "g a": 1,
    "rwa": 1,
    "rds": 1,
    ", D": 1,
    "uke": 5,
    " di": 2,
    "sco": 1,
    "ver": 2,
    "s B": 1,
    "o e": 1,
    "xpl": 1,
    "ori": 4,
    ". T": 3,
    "two": 2,
    "com": 1,
    "e f": 2,
    "nds": 1,
    ", f": 1,
    "or ": 2,
    "e k": 1,
    "now": 1,
    "s a": 5,
    "bou": 2,
    "t h": 3,
    "ow ": 1,
    "sav": 1,
    " ch": 1,
    "ild": 2,
    "ren": 1,
    "nex": 1,
    "t d": 1,
    "ay,": 1,
    "e r": 3,
    "ace": 3,
    " ab": 1,
    "out": 1,
    "gin": 2,
    "s b": 1,
    "oas": 1,
    "how": 1,
    "d t": 2,
    "o S": 1,
    "tel": 2,
    "la,": 2,
    " un": 1,
    "awa": 2,
    "re ": 1,
    "tha": 5,
    "t s": 1,
    "s r": 1,
    "igh": 1,
    "t b": 1,
    "ehi": 1,
    ". S": 1,
    "bec": 1,
    "s v": 1,
    "ery": 1,
    " an": 11,
    "gry": 2,
    "d m": 1,
    "ana": 1,
    "ges": 1,
    " ge": 1,
    "im ": 2,
    "stu": 1,
    "ck ": 1,
    "one": 3,
    "e m": 1,
    " ba": 2,
    "gs,": 1,
    " wh": 3,
    "ich": 1,
    " ho": 1,
    "ist": 1,
    "ont": 1,
    "o t": 2,
    "ne.": 1,
    "tow": 1,
    "n o": 1,
    "f W": 1,
    "hit": 1,
    "e M": 1,
    "oun": 1,
    "tai": 1,
    "n a": 1,
    "bac": 3,
    "k. ": 1,
    "At ": 1,
    "fir": 1,
    "st,": 1,
    "e e": 3,
    "asi": 1,
    "ove": 1,
    "rta": 1,
    "kes": 1,
    "e d": 2,
    "ogs": 1,
    "on ": 1,
    "y b": 2,
    "ack": 1,
    ", t": 1,
    "ne ": 1,
    "mys": 1,
    "ter": 1,
    "iou": 1,
    "sly": 1,
    "sap": 1,
    "pea": 1,
    "rs.": 1,
    "og ": 1,
    "m w": 1,
    "i i": 1,
    "s c": 2,
    "onf": 1,
    "ide": 1,
    "job": 2,
    "cur": 1,
    "But": 1,
    "ill": 1,
    "ubt": 1,
    "t, ": 1,
    "muc": 1,
    "h t": 1,
    "dis": 1,
    "may": 1,
    ". W": 1,
    "hen": 1,
    "e s": 2,
    "til": 1,
    "l h": 2,
    "asn": 1,
    "'t ": 1,
    "arr": 1,
    "ive": 1,
    "d y": 1,
    "et,": 1,
    "spe": 1,
    "cts": 1,
    "som": 1,
    "eth": 1,
    " ha": 2,
    "s g": 1,
    " wr": 1,
    "ong": 1,
    "ets": 1,
    " ou": 1,
    "o r": 1,
    "esc": 1,
    "ue ": 1,
    "ref": 1,
    "use": 2,
    "elp": 3,
    ", s": 1,
    "ayi": 1,
    "t D": 1,
    "nem": 1,
    "eca": 1,
    " tr": 1,
    "ied": 1,
    " ta": 1,
    "ke ": 2,
    "y K": 1,
    "r B": 1,
    "o l": 1,
    "eav": 1,
    "es,": 1,
    " Je": 1,
    "nna": 1,
    "rpr": 1,
    "ise": 2,
    "d a": 1,
    "ang": 1,
    "ry ": 1,
    "t K": 2,
    "d n": 1,
    "gon": 1,
    "d v": 1,
    "alu": 1,
    "b o": 1,
    "hum": 1,
    "an ": 1,
    "lif": 1,
    "i r": 1,
    "eal": 1,
    " it": 1,
    "s d": 1,
    "uty": 1,
    "lp ": 2,
    " fa": 1,
    "r. ": 1,
    "On ": 1,
    "mee": 1,
    "up ": 1,
    "wit": 1,
    "h S": 1,
    "o s": 1,
    "ays": 1,
    "was": 1,
    " on": 2,
    "oo.": 1,
    "a i": 1,
    "ngr": 1,
    ", b": 2,
    "she": 3,
    " al": 1,
    "so ": 1,
    "mis": 1,
    "sin": 2,
    "g B": 1,
    "adm": 1,
    "its": 1,
    "o c": 1,
    " in": 2,
    "ilb": 1,
    "ag.": 1,
    " Wi": 1,
    "th ": 1,
    "Ste": 3,
    "lla": 3,
    "Muk": 1,
    "d L": 1,
    "uk,": 1,
    "cat": 1,
    "es ": 3,
    " si": 1,
    "te ": 1,
    " cr": 1,
    "ash": 1,
    "nco": 1,
    "unt": 1,
    " mo": 1,
    "s q": 1,
    "uic": 1,
    "kly": 1,
    " fo": 1,
    "und": 2,
    "pol": 1,
    "ar ": 1,
    "bea": 1,
    "hea": 1,
    "hom": 1,
    "sta": 1,
    "ys ": 1,
    "beh": 1,
    "ind": 2,
    " (w": 1,
    "hos": 1,
    "e l": 1,
    "eg ": 1,
    "bro": 1,
    "ken": 1,
    ") a": 1,
    "tri": 1,
    "hau": 1,
    "k t": 2,
    "o N": 2,
    "et ": 1,
    "met": 1,
    "al.": 1,
    " Bu": 1,
    "t o": 1,
    "way": 1,
    "ck,": 1,
    " ic": 1,
    "rid": 1,
    "t B": 1,
    "ros": 1,
    "g b": 1,
    "rea": 1,
    " fe": 1,
    "et.": 1,
    "d D": 2,
    "o f": 2,
    "all": 2,
    "a c": 1,
    "any": 1,
    "on,": 1,
    "ve ": 2,
    "t i": 1,
    "ime": 1,
    " sa": 1,
    "m b": 1,
    "oth": 1,
    "s h": 1,
    " br": 1,
    " Du": 2,
    "d B": 1,
    "s p": 1,
    "her": 1,
    "o, ": 1,
    "onc": 1,
    "gai": 1,
    "n. ": 1,
    "giv": 1,
    "is,": 1,
    "w p": 1,
    "\"Ba": 1,
    " Fl": 1,
    "yer": 1,
    "\" w": 1,
    "hic": 1,
    "h B": 1,
    "n w": 1,
    "ke.": 1
  },
  "qualityClass": 2
}
