{
  "posTrigrams": {
    "NNP,NNP,JJ": 1,
    "CD,NNP,CD": 4,
    "VBD,DT,JJ": 3,
    "PRP,VBD,DT": 4,
    "NN,CC,VBG": 1,
    "NN,IN,DT": 13,
    "NNP,IN,NNP": 8,
    "CC,RB,VBD": 1,
    "DT,JJ,NN": 8,
    "IN,DT,NN": 13,
    "JJ,POS,JJS": 1,
    "JJ,NN,VBD": 1,
    "JJ,NN,IN": 10,
    "DT,JJ,VBD": 2,
    "VBN,IN,CD": 3,
    "NNP,CD,IN": 2,
    "NNP,NNP,NNP": 14,
    "TO,NNP,NNP": 2,
    "JJ,CD,CD": 1,
    "CC,NNP,NNP": 3,
    "JJ,NN,SYM": 1,
    "NNP,CD,CD": 1,
    "IN,JJ,NNS": 8,
    "IN,PRP$,NN": 3,
    "PRP,VBD,JJ": 1,
    "VBN,TO,NN": 1,
    "WRB,PRP,VBD": 2,
    "NNS,IN,NNP": 1,
    "NNP,NNP,POS": 2,
    "NNP,NNP,VBN": 2,
    "IN,NNP,NNP": 8,
    "IN,DT,NNS": 5,
    "IN,CD,PRP": 4,
    "VBD,TO,DT": 2,
    "NNP,NNPS,VBG": 1,
    "NNP,IN,CD": 3,
    "DT,NNP,JJ": 1,
    "WDT,VBD,IN": 2,
    "NNP,NNP,IN": 6,
    "IN,CD,IN": 2,
    "PRP$,NN,DT": 1,
    "NNP,NNP,DT": 3,
    "DT,NNP,NN": 1,
    "NNS,RB,NNP": 1,
    "POS,CC,DT": 1,
    "NN,IN,NN": 2,
    "NNS,VBG,DT": 1,
    "JJ,NNP,NNP": 4,
    "CC,VBG,NNS": 1,
    "VBN,IN,NNP": 1,
    "POS,NN,IN": 1,
    "DT,NN,IN": 9,
    "DT,NNP,NNP": 7,
    "IN,DT,NNP": 5,
    "NNP,VBD,NN": 2,
    "NNS,MD,VB": 2,
    "NN,NNS,IN": 1,
    "PRP,VBD,IN": 4,
    "DT,NN,WDT": 1,
    "NNP,NNP,CC": 5,
    "NNP,NNP,VBD": 2,
    "VBN,IN,DT": 3,
    "VBG,NN,IN": 1,
    "DT,NNP,IN": 1,
    "RB,IN,CD": 2,
    "JJ,VBD,VBN": 1,
    "IN,DT,JJ": 8,
    "NN,VBD,DT": 1,
    "NN,IN,JJ": 3,
    "NNS,IN,DT": 3,
    "JJ,JJ,NNS": 1,
    "CC,IN,CD": 1,
    "NNP,CD,DT": 1,
    "VBD,RB,VBN": 2,
    "IN,CD,NN": 1,
    "NNP,VBD,IN": 2,
    "DT,RB,VBN": 1,
    "NN,VBP,DT": 1,
    "JJ,NN,CC": 4,
    "VBD,TO,VB": 3,
    "NN,CC,NN": 2,
    "IN,NNP,DT": 1,
    "JJ,JJ,NNP": 1,
    "VBD,NNP,NNP": 1,
    "NN,VBG,NN": 1,
    "CC,CD,IN": 1,
    "PRP$,NN,IN": 3,
    "JJ,VBN,IN": 1,
    "DT,CD,NNP": 5,
    "CD,CC,CD": 1,
    "CC,VBD,DT": 1,
    "VBD,VBN,DT": 1,
    "JJ,IN,DT": 4,
    "NN,IN,NNP": 2,
    "IN,CD,NNP": 2,
    "CD,JJ,VBD": 1,
    "DT,NN,JJ": 1,
    "NN,VBN,IN": 1,
    "DT,JJ,CD": 2,
    "CD,NNP,NNP": 4,
    "VBD,IN,NNP": 2,
    "IN,DT,CD": 1,
    "NNP,NNP,RB": 1,
    "VBN,IN,PRP$": 1,
    "NN,NN,IN": 3,
    "NNP,JJ,VBN": 1,
    "NN,CD,IN": 2,
    "NN,CC,JJ": 1,
    "NNS,CC,MD": 1,
    "RB,VB,TO": 1,
    "CD,IN,NN": 1,
    "CD,WRB,DT": 1,
    "PRP,VBD,RP": 1,
    "VBG,DT,NN": 2,
    "IN,CD,NNS": 2,
    "NNP,NNPS,CC": 1,
    "NN,VBG,JJ": 1,
    "NN,NNS,CC": 2,
    "WRB,PRP,VBP": 1,
    "DT,IN,PRP$": 1,
    "NN,VBD,IN": 2,
    "POS,DT,NN": 1,
    "JJS,PRP$,NN": 1,
    "TO,VB,NN": 2,
    "PRP,VBP,TO": 1,
    "VB,DT,NN": 2,
    "IN,PRP$,JJ": 2,
    "VBD,TO,NNP": 1,
    "VBD,DT,NN": 3,
    "RB,VBG,TO": 1,
    "DT,NN,VBG": 1,
    "NNP,CC,DT": 3,
    "CD,JJ,VBN": 1,
    "IN,JJ,NNP": 1,
    "NNP,TO,VB": 1,
    "IN,JJ,NN": 2,
    "VBG,CD,IN": 1,
    "DT,NN,NN": 3,
    "WDT,VBD,VBN": 1,
    "VBD,VBN,IN": 3,
    "CD,IN,DT": 1,
    "NN,IN,NNS": 2,
    "DT,NN,VBZ": 1,
    "IN,JJ,JJ": 1,
    "JJ,NNS,CC": 1,
    "JJ,NN,NNS": 1,
    "VBN,IN,NN": 1,
    "IN,IN,NNS": 1,
    "NNS,RB,CC": 1,
    "NNS,RB,RB": 1,
    "TO,NNS,VBN": 1,
    "VBP,JJ,NNS": 1,
    "WDT,RB,DT": 1,
    "NN,VB,DT": 1,
    "DT,NN,CC": 2,
    "DT,JJ,JJ": 3,
    "NN,WDT,VBZ": 1,
    "NNS,IN,NNS": 1,
    "WDT,RB,VBP": 1,
    "JJ,VBD,JJ": 1,
    "CD,NNS,NN": 1,
    "NN,IN,CD": 3,
    "DT,NN,VBD": 2,
    "CD,NNP,JJ": 1,
    "DT,NNS,NN": 1,
    "CD,DT,JJ": 1,
    "VB,PRP,VB": 1,
    "RB,CD,NNS": 2,
    "VBZ,VBN,IN": 2,
    "IN,RB,JJ": 2,
    "NN,MD,VB": 2,
    "PRP,MD,VB": 1,
    "JJ,NNS,VBG": 1,
    "IN,PRP,VBP": 1,
    "JJ,POS,JJ": 1,
    "NN,VBD,TO": 1,
    "VB,VBN,IN": 1,
    "NN,JJ,IN": 1,
    "VBG,PRP$,NN": 1,
    "NNS,VBP,RP": 1,
    "JJ,IN,JJ": 1,
    "NNS,CC,JJ": 1,
    "JJ,VBN,TO": 1,
    "VB,PRP$,NN": 1,
    "NN,TO,DT": 2,
    "JJR,NN,RB": 1,
    "RB,VBN,IN": 1,
    "VBN,TO,VB": 2,
    "NN,NN,NN": 1,
    "JJ,VBD,DT": 2,
    "NN,NN,VBZ": 1,
    "TO,VB,JJ": 2,
    "VBD,IN,DT": 2,
    "IN,DT,RB": 2,
    "VBN,NN,RB": 1,
    "PRP$,NNS,VBD": 2,
    "WP,VBD,PRP": 1,
    "RB,CC,RB": 1,
    "VBN,JJR,IN": 1,
    "DT,RB,JJ": 1,
    "PRP,VBD,RB": 1,
    "VBN,NNS,WDT": 1,
    "VBD,JJ,NN": 1,
    "NN,TO,VB": 4,
    "VBG,IN,DT": 1,
    "JJ,CC,IN": 1,
    "JJ,VBZ,VBN": 1,
    "IN,VBG,DT": 1,
    "JJ,NN,NN": 4,
    "JJ,VBN,DT": 1,
    "JJ,NN,DT": 1,
    "JJ,JJ,NN": 2,
    "NNP,CC,NNP": 1,
    "NNP,VBZ,IN": 1,
    "DT,NN,PRP": 1,
    "VBG,CD,NNS": 1,
    "VBN,IN,NNS": 1,
    "DT,NN,RB": 1,
    "VBZ,JJ,JJ": 1,
    "TO,JJ,NN": 1,
    "RB,RB,IN": 1,
    "DT,CD,NN": 1,
    "IN,NNP,VBD": 1,
    "DT,NN,TO": 1,
    "VB,DT,IN": 1,
    "JJ,POS,NN": 5,
    "NNP,JJ,POS": 1,
    "VBG,VBD,DT": 1,
    "JJ,NN,VBG": 1,
    "DT,JJ,CC": 1,
    "PRP,VBD,NNS": 1,
    "WDT,VBD,RB": 1,
    "VBD,NNS,VBG": 1,
    "TO,JJ,NNS": 1,
    "VBN,IN,CC": 1,
    "PRP,VBD,PRP": 1,
    "IN,IN,DT": 1,
    "NN,CC,IN": 1,
    "NNS,CC,NNS": 1,
    "VBG,IN,WP": 1,
    "NN,PRP,MD": 1,
    "VB,NN,IN": 1,
    "PRP$,NN,NN": 1,
    "NNS,VBD,RB": 1,
    "RBR,JJ,IN": 1,
    "NNP,WRB,PRP": 1,
    "NNS,IN,NN": 1,
    "NN,NNP,NNP": 2,
    "NNP,VBD,RB": 2,
    "JJ,DT,NN": 1,
    "NN,VBD,VBN": 1,
    "TO,NN,RB": 1,
    "RB,IN,JJ": 1,
    "IN,EX,VBZ": 1,
    "NN,NN,PRP": 1,
    "MD,RB,VB": 1,
    "JJ,TO,DT": 1,
    "NN,IN,PRP$": 1,
    "CC,PRP$,NN": 1,
    "NNS,CC,RB": 2,
    "JJ,NNS,IN": 3,
    "PRP$,JJ,NNS": 1,
    "RB,JJ,CD": 1,
    "IN,VBN,RB": 1,
    "DT,JJS,IN": 1,
    "NNS,JJ,NNS": 1,
    "MD,VB,RP": 1,
    "TO,DT,NNS": 1,
    "IN,NNS,CC": 1,
    "NNS,VBG,JJ": 1,
    "NNS,WP$,NNS": 1,
    "VBD,JJ,CC": 1,
    "RB,VBG,DT": 1,
    "JJS,NNS,IN": 1,
    "PRP$,NN,VBG": 1,
    "NN,NN,CC": 1,
    "DT,JJ,NNP": 1,
    "NNP,VBZ,JJ": 1,
    "WDT,VBP,DT": 1,
    "RB,JJ,CC": 1,
    "NN,WDT,VBD": 1,
    "RB,RB,JJ": 1,
    "IN,NN,CC": 2,
    "TO,VB,RB": 1,
    "JJ,CC,JJ": 1,
    "NNS,WDT,VBP": 1,
    "JJ,TO,NN": 1,
    "CC,RB,VBP": 1,
    "RBR,VBN,VBG": 1,
    "CC,JJ,IN": 1,
    "JJS,JJ,NN": 1,
    "DT,JJ,NNS": 1,
    "IN,PRP,VBD": 1,
    "CC,VBD,IN": 1,
    "DT,JJ,JJS": 1,
    "NNP,VBD,DT": 1,
    "VBD,CD,CD": 1,
    "NNP,IN,DT": 2,
    "NN,NNP,IN": 1,
    "NN,CD,VBD": 1,
    "PRP$,JJ,NNP": 1,
    "NNP,NN,IN": 1,
    "CD,NNS,RB": 1,
    "JJ,VBD,IN": 2,
    "VBD,VBN,TO": 1,
    "RB,NNP,NN": 1,
    "NNP,CD,VBD": 1,
    "TO,JJ,IN": 1,
    "NN,IN,PRP": 2,
    "VBD,RB,RB": 1,
    "IN,NNS,CD": 1,
    "CC,CD,VBG": 1,
    "RB,CC,IN": 1,
    "RB,DT,VBG": 1,
    "NN,VBD,PRP": 1,
    "PRP$,JJ,NN": 4,
    "TO,VB,DT": 1,
    "NNS,VBD,JJ": 1,
    "NN,PRP,VBD": 1,
    "PRP,VBD,VBN": 1,
    "NN,CC,PRP": 1,
    "VBD,IN,PRP$": 1,
    "NN,VBD,RB": 1,
    "NNS,VBD,VBN": 1,
    "JJ,CD,NNS": 2,
    "VBD,PRP,IN": 1,
    "CD,VBN,IN": 1,
    "NNP,CD,NNS": 1,
    "NN,NN,NNP": 1,
    "WP,VBD,IN": 1,
    "VBD,JJ,IN": 1,
    "PRP$,NN,RB": 1,
    "RB,VBD,NNS": 1,
    "CC,NNS,CC": 1,
    "RB,VBD,PRP": 1,
    "VBN,JJ,NN": 1,
    "NNS,CD,CD": 1,
    "NN,CD,RB": 1,
    "PRP,VBD,TO": 1,
    "CC,PRP,MD": 1,
    "RB,VB,IN": 1,
    "CD,CD,TO": 1,
    "PRP,VBD,CD": 1,
    "VB,JJ,RB": 1,
    "SYM,DT,NN": 1,
    "IN,NNP,SYM": 1,
    "VBD,RB,VB": 1,
    "JJ,NNP,SYM": 1,
    "VBN,DT,NN": 1,
    "VBD,JJ,NNP": 1,
    "VBZ,DT,NN": 1,
    "JJ,NNP,NN": 1,
    "JJ,JJ,CD": 1,
    "NNS,CD,IN": 1,
    "CD,CD,IN": 1,
    "CC,DT,JJ": 1,
    "IN,PRP$,NNS": 1,
    "CD,TO,NNP": 1,
    "NNP,NNP,CD": 1,
    "CD,DT,NN": 1,
    "CD,NNS,PRP$": 1,
    "PRP$,JJ,VBG": 1,
    "VBD,CD,NN": 1,
    "CC,DT,NN": 1,
    "PRP,VBZ,RB": 1,
    "JJ,RB,RB": 1,
    "VBN,IN,JJ": 1,
    "NN,DT,CD": 1,
    "NNP,NN,VBD": 1,
    "PRP,IN,DT": 1
  },
  "characterTrigrams": {
    "147": 1,
    "149": 1,
    "168": 1,
    "188": 3,
    "189": 1,
    "190": 1,
    "191": 2,
    "192": 1,
    "194": 2,
    "200": 1,
    "850": 1,
    "899": 1,
    "902": 1,
    "904": 1,
    "905": 3,
    "916": 1,
    "917": 1,
    "939": 1,
    "940": 1,
    "944": 2,
    "947": 1,
    "954": 1,
    "Her": 1,
    "ber": 5,
    "t B": 1,
    "ert": 2,
    "ram": 1,
    " St": 15,
    "ron": 12,
    "g (": 1,
    "13 ": 3,
    "Feb": 2,
    "rua": 2,
    "ry ": 8,
    "0 –": 1,
    " 8 ": 2,
    "Oct": 3,
    "obe": 3,
    "r 1": 2,
    ") w": 1,
    "as ": 14,
    "an ": 15,
    "Eng": 4,
    "lis": 2,
    "h p": 2,
    "rof": 1,
    "ess": 4,
    "ion": 9,
    "al ": 4,
    "gol": 5,
    "fer": 4,
    ". H": 5,
    "e w": 8,
    "org": 4,
    "ani": 3,
    "zer": 1,
    " an": 22,
    "d f": 3,
    "oun": 9,
    "din": 2,
    "g m": 3,
    "emb": 3,
    "er ": 9,
    "of ": 18,
    "the": 40,
    " PG": 1,
    "A o": 1,
    "f A": 1,
    "mer": 1,
    "ica": 3,
    "d l": 2,
    "ate": 8,
    "r b": 2,
    "eca": 1,
    "me ": 6,
    "a s": 1,
    "ucc": 1,
    "ful": 3,
    " go": 4,
    "lf ": 6,
    "cou": 8,
    "rse": 11,
    " ar": 6,
    "chi": 4,
    "tec": 5,
    "t. ": 3,
    "As ": 1,
    "a p": 5,
    "lay": 11,
    "er,": 3,
    "g's": 2,
    " be": 8,
    "st ": 7,
    "fin": 2,
    "ish": 3,
    " in": 24,
    " a ": 14,
    "maj": 1,
    "or ": 7,
    "cha": 2,
    "mpi": 4,
    "ons": 5,
    "hip": 4,
    " wa": 7,
    "s n": 2,
    "int": 4,
    "lac": 2,
    "e i": 5,
    "n t": 7,
    "he ": 39,
    "  S": 4,
    "tro": 16,
    "ng ": 17,
    "was": 9,
    " bo": 3,
    "rn ": 1,
    "on ": 15,
    "0 i": 2,
    "n R": 1,
    "ams": 1,
    "gat": 3,
    "e, ": 4,
    "Ken": 1,
    "t, ": 1,
    "lan": 1,
    "d, ": 2,
    "to ": 15,
    "Wil": 1,
    "lia": 1,
    "m R": 1,
    ". S": 5,
    "(18": 1,
    "46–": 1,
    "9) ": 1,
    "and": 28,
    " Ch": 4,
    "arl": 1,
    "ott": 1,
    "e E": 1,
    "née": 1,
    "ock": 1,
    " (1": 1,
    "–19": 1,
    "23)": 1,
    ". L": 1,
    "ike": 1,
    " ma": 4,
    "ny ": 1,
    "s f": 2,
    "rom": 1,
    " hi": 15,
    "s e": 4,
    "ra,": 1,
    " he": 9,
    "irs": 5,
    "t i": 5,
    "ntr": 4,
    "odu": 1,
    "ced": 2,
    " to": 19,
    "via": 1,
    "s p": 2,
    "art": 5,
    "ici": 2,
    "pat": 1,
    " as": 6,
    "cad": 2,
    "dy ": 2,
    "whe": 1,
    "n h": 4,
    "e t": 8,
    "ote": 1,
    "d b": 4,
    "ags": 1,
    " at": 4,
    " Ro": 4,
    "yal": 2,
    " Ge": 2,
    "e's": 2,
    " Go": 3,
    "Clu": 6,
    "b l": 2,
    "oca": 2,
    "ted": 9,
    " Sa": 2,
    "ndw": 2,
    "ich": 5,
    ", E": 2,
    "ngl": 2,
    ", i": 3,
    "mid": 1,
    "-18": 1,
    "90s": 1,
    ". I": 2,
    "n 1": 7,
    " em": 1,
    "igr": 1,
    "d t": 11,
    "o t": 5,
    "Uni": 1,
    "s, ": 8,
    "dep": 2,
    "ing": 21,
    " Li": 1,
    "ver": 7,
    "poo": 4,
    "l o": 2,
    "4 J": 1,
    "une": 1,
    " 19": 15,
    "05 ": 2,
    "abo": 1,
    "ard": 4,
    " th": 55,
    "e S": 2,
    "S \"": 1,
    "Teu": 1,
    "ton": 2,
    "ic\"": 1,
    " wh": 5,
    "riv": 1,
    "ed ": 32,
    "in ": 19,
    "New": 3,
    " Yo": 3,
    "rk ": 2,
    "22 ": 1,
    "Jun": 1,
    "e 1": 7,
    " wi": 11,
    "th ": 10,
    "$40": 1,
    "is ": 13,
    "poc": 1,
    "ket": 1,
    ", a": 5,
    "fty": 1,
    " su": 3,
    "m a": 1,
    "t t": 7,
    "tim": 5,
    "e. ": 4,
    "dma": 1,
    "n W": 1,
    "ana": 2,
    "mak": 4,
    "eal": 1,
    "thy": 1,
    " pr": 7,
    "opr": 1,
    "iet": 1,
    " Wa": 5,
    "nam": 6,
    "ake": 5,
    "r d": 1,
    "epa": 1,
    "rtm": 1,
    "ent": 6,
    " st": 6,
    "ore": 4,
    "s (": 1,
    "now": 1,
    " Ma": 5,
    "cy'": 1,
    "s),": 1,
    "d a": 9,
    " nu": 1,
    "mbe": 2,
    "r o": 3,
    "f g": 3,
    "olf": 8,
    "ofe": 3,
    "ssi": 5,
    "ona": 4,
    "ls—": 1,
    "inc": 2,
    "lud": 1,
    "e l": 1,
    "ege": 1,
    "nda": 1,
    "Wal": 2,
    "ter": 10,
    " Ha": 1,
    "gen": 1,
    "ead": 1,
    " am": 1,
    "urs": 13,
    " of": 22,
    "e e": 5,
    "ra—": 2,
    "her": 8,
    "at ": 20,
    "Wan": 1,
    "ama": 3,
    "ker": 2,
    "'s ": 3,
    "inv": 1,
    "ita": 1,
    "tio": 3,
    "n f": 1,
    "a l": 1,
    "unc": 1,
    "heo": 1,
    "n a": 10,
    "Tap": 2,
    "low": 3,
    " Cl": 5,
    "ub ": 3,
    "rti": 3,
    "niq": 1,
    "ue ": 1,
    "Hot": 1,
    "el ": 3,
    "Bro": 2,
    "adw": 1,
    "ay ": 2,
    " We": 1,
    "32n": 1,
    "d S": 3,
    "tre": 2,
    "et ": 1,
    "Cit": 1,
    "y o": 2,
    "7 J": 1,
    "anu": 1,
    "ary": 1,
    "16.": 1,
    "eli": 1,
    "eve": 9,
    "d g": 2,
    "ls ": 2,
    "ld ": 8,
    "enh": 2,
    "anc": 7,
    "qui": 1,
    "pme": 1,
    "nt ": 2,
    "sal": 1,
    "es ": 14,
    "if ": 1,
    "y f": 3,
    "orm": 3,
    "ass": 2,
    "oci": 1,
    "ati": 1,
    "on.": 1,
    " It": 1,
    "s d": 2,
    "uri": 2,
    "thi": 2,
    "s m": 2,
    "eet": 2,
    "Str": 8,
    "ong": 9,
    ", J": 2,
    "ame": 3,
    "s H": 2,
    "epb": 1,
    "urn": 2,
    "ack": 3,
    " Ho": 1,
    "ben": 1,
    "Jac": 1,
    "k M": 1,
    "ie,": 1,
    " Ja": 1,
    "mes": 1,
    "ide": 3,
    "n, ": 3,
    "Gil": 1,
    "t N": 1,
    "oll": 2,
    "s a": 10,
    "nd ": 26,
    "Rob": 1,
    " Wh": 1,
    "ite": 7,
    " we": 4,
    "re ": 12,
    "cho": 1,
    "sen": 1,
    "e o": 8,
    "rga": 1,
    "niz": 2,
    " co": 18,
    "mmi": 1,
    "tte": 2,
    "f t": 7,
    "PGA": 5,
    " Am": 2,
    "eri": 3,
    "ca.": 1,
    " La": 1,
    "16,": 1,
    "g w": 3,
    "app": 3,
    "oin": 1,
    "e f": 9,
    "t S": 2,
    "ecr": 1,
    "eta": 1,
    "ry-": 1,
    "Tre": 1,
    "asu": 1,
    "rer": 1,
    ". T": 5,
    "iti": 2,
    " se": 5,
    "rie": 2,
    "s o": 7,
    "f s": 2,
    "ral": 5,
    " me": 2,
    "eti": 1,
    "ngs": 1,
    " ov": 1,
    " ne": 2,
    "xt ": 1,
    "sev": 5,
    "era": 1,
    "l m": 1,
    "ont": 3,
    "hs ": 1,
    ", o": 1,
    "0 A": 1,
    "pri": 2,
    "l 1": 1,
    ", t": 3,
    "ca ": 1,
    "fic": 1,
    "ial": 1,
    "ly ": 10,
    "est": 4,
    "abl": 2,
    "wit": 5,
    "h 3": 1,
    "5 c": 1,
    "har": 1,
    "rs.": 4,
    "r p": 2,
    "rop": 4,
    "ose": 3,
    "hat": 9,
    "e n": 4,
    "ewl": 1,
    "zat": 1,
    " ho": 7,
    "ann": 1,
    "ual": 3,
    "nt,": 1,
    "d o": 2,
    "ffe": 1,
    "red": 5,
    " do": 1,
    "nat": 1,
    "e m": 3,
    "one": 5,
    "a t": 1,
    "hy ": 4,
    "ize": 3,
    " fu": 1,
    "nd.": 3,
    " Th": 9,
    "r, ": 3,
    " fi": 8,
    "rst": 3,
    "nua": 1,
    "l P": 1,
    "GA ": 1,
    "Cha": 3,
    "ok ": 1,
    "pla": 8,
    "ce ": 4,
    " Si": 1,
    "wan": 1,
    "oy ": 1,
    "Cou": 3,
    "y C": 2,
    "lub": 7,
    " Br": 1,
    "onx": 1,
    "vil": 1,
    "le,": 1,
    " Ne": 1,
    "w Y": 1,
    "ork": 2,
    ". J": 1,
    "s M": 1,
    ". B": 2,
    "arn": 2,
    "def": 3,
    "eat": 4,
    "Joc": 1,
    "k H": 1,
    "utc": 1,
    "his": 7,
    " ch": 2,
    "amp": 4,
    "shi": 4,
    "p m": 3,
    "atc": 3,
    "h, ": 3,
    "tak": 1,
    "r T": 1,
    " $2": 1,
    ",58": 1,
    "0 a": 3,
    "s h": 4,
    "sha": 4,
    " pu": 4,
    ".  ": 2,
    "mpe": 1,
    " Op": 5,
    "en ": 13,
    "e p": 5,
    "teu": 1,
    "sco": 2,
    " 89": 1,
    "d 9": 1,
    "mis": 1,
    "sed": 2,
    "e c": 8,
    "ut ": 3,
    "by ": 2,
    "8 s": 1,
    "kes": 2,
    "y 1": 1,
    " ha": 2,
    "eco": 5,
    "l a": 5,
    "Gog": 1,
    "gog": 1,
    "b n": 1,
    "ear": 6,
    " Ca": 2,
    "mbr": 1,
    "idg": 1,
    "In ": 2,
    "a f": 1,
    "ndl": 1,
    "y m": 1,
    "h a": 3,
    "gai": 3,
    "nst": 1,
    " To": 1,
    "m V": 1,
    "San": 1,
    "dwi": 1,
    "ch ": 3,
    "27 ": 2,
    "May": 1,
    "03,": 1,
    "ade": 2,
    "hol": 4,
    "e-i": 1,
    "n-o": 1,
    "ne ": 3,
    "(li": 1,
    "kel": 1,
    "y w": 2,
    "ind": 3,
    "sis": 1,
    ") o": 1,
    " pa": 3,
    "r 4": 1,
    "le.": 2,
    " He": 4,
    " en": 1,
    "03 ": 1,
    "Ope": 2,
    "n C": 1,
    "ham": 1,
    "pio": 1,
    "nsh": 2,
    "ip ": 1,
    "hel": 4,
    "t P": 3,
    "res": 1,
    "twi": 1,
    "ck ": 3,
    "Gol": 2,
    "f C": 2,
    ", S": 3,
    "out": 4,
    "h A": 1,
    "yrs": 1,
    "hir": 1,
    "Sco": 1,
    "tla": 1,
    "nd,": 1,
    " bu": 6,
    "t f": 2,
    "ail": 1,
    "adv": 2,
    "ast": 1,
    "e h": 12,
    "alf": 1,
    "-wa": 1,
    "y c": 2,
    "ut.": 1,
    " In": 1,
    "eld": 2,
    " on": 9,
    "ome": 6,
    "e a": 5,
    "wic": 2,
    " op": 1,
    "ene": 1,
    "d w": 3,
    "ith": 5,
    "fir": 2,
    "rou": 6,
    "93—": 1,
    "win": 3,
    "con": 3,
    "dit": 1,
    "s—b": 1,
    "onl": 2,
    "y i": 2,
    "mpr": 1,
    "ove": 2,
    " 88": 1,
    " ro": 4,
    "und": 4,
    " tw": 4,
    "o w": 1,
    "hen": 2,
    " im": 2,
    "pro": 4,
    "ved": 2,
    "nde": 2,
    "d u": 1,
    "iss": 2,
    "ut,": 1,
    " by": 6,
    " 13": 1,
    "rok": 2,
    "es,": 1,
    " ca": 1,
    ", h": 3,
    "mig": 1,
    "rat": 4,
    " Un": 2,
    "tat": 2,
    "cam": 1,
    "fes": 1,
    "sio": 2,
    "nal": 3,
    "e A": 1,
    "paw": 1,
    "ami": 1,
    "s C": 1,
    " Ry": 2,
    "rk,": 1,
    " fe": 2,
    "atu": 3,
    "rin": 3,
    "g p": 1,
    " la": 1,
    "for": 5,
    "ms ": 1,
    " bl": 1,
    " sh": 6,
    "ots": 3,
    ". W": 1,
    " yo": 1,
    "u c": 1,
    "omb": 1,
    "ine": 5,
    "h h": 3,
    "e s": 8,
    "pen": 3,
    "t a": 7,
    "t R": 1,
    "oya": 1,
    "l S": 1,
    "t G": 1,
    "eor": 1,
    "ge'": 1,
    "ere": 6,
    " le": 3,
    "y g": 1,
    ", y": 1,
    "ou ": 3,
    "sta": 2,
    "rt ": 5,
    "see": 2,
    "lot": 1,
    "rch": 4,
    "ctu": 2,
    "flu": 1,
    "enc": 1,
    "1, ": 2,
    "mov": 1,
    "Inw": 1,
    "ood": 2,
    " Co": 4,
    "unt": 4,
    "b a": 1,
    "rem": 1,
    "ode": 1,
    "led": 1,
    "our": 9,
    "se ": 5,
    "r s": 5,
    " ye": 1,
    "ars": 1,
    " ev": 5,
    "lea": 1,
    "g t": 5,
    "sti": 2,
    "21 ": 1,
    "p a": 2,
    "23 ": 1,
    "U.S": 3,
    ". O": 4,
    "6 S": 1,
    "ept": 2,
    "5 S": 1,
    "par": 2,
    "tne": 1,
    "18-": 2,
    "yea": 2,
    "r-o": 1,
    "Jer": 1,
    " Tr": 2,
    "ave": 3,
    "rs ": 4,
    "tie": 1,
    " fo": 8,
    "ce,": 2,
    "oot": 1,
    " 72": 1,
    "ur-": 1,
    "bal": 1,
    "l t": 3,
    "—pa": 1,
    "Met": 1,
    "oli": 1,
    "tan": 2,
    "en—": 1,
    "tha": 5,
    "t w": 1,
    "t F": 1,
    "ox ": 1,
    "Hil": 1,
    "n I": 1,
    "sla": 4,
    "   ": 1,
    "ers": 6,
    "b w": 1,
    "fou": 2,
    "d i": 1,
    "gro": 1,
    "up ": 1,
    "eng": 1,
    " fr": 2,
    "om ": 3,
    "Man": 2,
    "clu": 1,
    "b f": 1,
    "ure": 2,
    "tit": 2,
    "c u": 1,
    "ndu": 1,
    "lat": 2,
    " gr": 4,
    "een": 2,
    "mpl": 1,
    "exe": 1,
    "wid": 1,
    "ole": 6,
    "rri": 2,
    "dor": 1,
    "s b": 3,
    "uil": 2,
    "t o": 7,
    "err": 1,
    "ain": 2,
    "she": 1,
    "s u": 1,
    "pwa": 1,
    "rd ": 1,
    "cas": 1,
    "rpl": 1,
    "y d": 2,
    "own": 1,
    "war": 2,
    "o g": 1,
    "ree": 9,
    "ns ": 5,
    " dr": 1,
    "tic": 2,
    "nke": 3,
    " Wi": 1,
    "hos": 1,
    "sub": 1,
    "tle": 1,
    "uch": 1,
    "nly": 4,
    " fa": 2,
    "mil": 1,
    "iar": 1,
    "e r": 3,
    "gni": 1,
    "ze:": 1,
    "ell": 3,
    "-pl": 2,
    "ace": 3,
    "d r": 1,
    "air": 3,
    "way": 4,
    " or": 3,
    "lig": 1,
    "ht ": 1,
    "gre": 10,
    "tou": 2,
    "nds": 3,
    "tts": 2,
    " di": 1,
    "rec": 1,
    "t s": 2,
    "eem": 1,
    "y t": 2,
    "law": 1,
    "avi": 2,
    "ty.": 1,
    "o c": 2,
    "omp": 1,
    "let": 1,
    "tru": 2,
    "cti": 2,
    "mon": 2,
    "ths": 1,
    " ti": 4,
    "me.": 1,
    " De": 1,
    "eux": 1,
    " Em": 1,
    "met": 3,
    " re": 8,
    "mod": 1,
    "ele": 2,
    "d p": 2,
    "1. ": 1,
    "The": 2,
    "ost": 2,
    "19 ": 2,
    "20 ": 1,
    ". A": 4,
    "mat": 2,
    "eur": 2,
    " sp": 2,
    "ort": 2,
    "s w": 3,
    "rit": 3,
    "wro": 1,
    "te ": 2,
    "Aug": 1,
    "ust": 1,
    "20:": 1,
    " \"N": 1,
    "o y": 1,
    "g c": 2,
    "ist": 2,
    "ory": 1,
    "lf,": 1,
    "t g": 1,
    "o b": 2,
    " 40": 2,
    "0 y": 1,
    "has": 1,
    " mu": 1,
    "dis": 2,
    "cus": 1,
    "com": 2,
    "men": 4,
    "s E": 1,
    "ngi": 2,
    "nee": 2,
    "rve": 1,
    " te": 1,
    "wil": 2,
    "l b": 1,
    "ens": 5,
    ". Y": 1,
    "l f": 2,
    "wee": 1,
    "pin": 1,
    "g a": 3,
    "s t": 4,
    "hey": 2,
    "nis": 3,
    "\". ": 2,
    "tur": 5,
    "wor": 1,
    "k w": 1,
    "be ": 1,
    "ded": 4,
    "ais": 1,
    " it": 1,
    "rig": 2,
    "ina": 4,
    "lit": 1,
    "y. ": 3,
    "He ": 3,
    "exc": 1,
    "s g": 3,
    "fea": 3,
    "suc": 1,
    "ult": 1,
    "i-t": 1,
    "ier": 2,
    "d d": 2,
    "eep": 1,
    ", c": 1,
    "rno": 1,
    "us ": 1,
    "bun": 1,
    "s. ": 1,
    "nag": 1,
    "rm ": 1,
    "a h": 3,
    "igh": 1,
    "lev": 1,
    "not": 2,
    " al": 1,
    "ppr": 2,
    "oac": 2,
    "hed": 2,
    " ot": 1,
    "ts.": 2,
    " As": 1,
    "ked": 1,
    "ula": 1,
    " ph": 1,
    "ilo": 1,
    "sop": 1,
    "f c": 2,
    "des": 4,
    "ign": 4,
    "sai": 1,
    "\"th": 2,
    "e d": 3,
    "uty": 1,
    "e g": 3,
    "d n": 1,
    "aut": 1,
    "nto": 1,
    "ery": 1,
    " po": 1,
    "ble": 5,
    "y.\"": 1,
    "lie": 4,
    "eed": 3,
    "r g": 2,
    "ot-": 1,
    "elt": 1,
    "sho": 4,
    "uld": 1,
    "y a": 3,
    "gh ": 1,
    "rly": 2,
    " ex": 3,
    "ecu": 1,
    "ot—": 1,
    "occ": 1,
    "asi": 1,
    "lly": 4,
    "ire": 1,
    "sul": 1,
    " Hi": 2,
    "wer": 4,
    "t h": 2,
    "im ": 4,
    "apa": 1,
    "ten": 1,
    "t m": 2,
    "tra": 3,
    "teg": 1,
    "han": 2,
    "qua": 1,
    " da": 2,
    " de": 4,
    "sig": 4,
    "ned": 4,
    "ldl": 1,
    "req": 1,
    "uir": 1,
    "car": 1,
    "efu": 1,
    "fro": 3,
    "m t": 2,
    "sid": 1,
    "fai": 1,
    "rwa": 1,
    "y, ": 2,
    "avo": 1,
    "id ": 1,
    "run": 1,
    "nin": 1,
    "hro": 1,
    "ugh": 3,
    "yon": 1,
    "d. ": 1,
    " is": 1,
    " cr": 2,
    "edi": 1,
    "es.": 2,
    "g d": 1,
    "esi": 4,
    "gne": 1,
    "t-c": 1,
    "opi": 1,
    "lle": 1,
    "nge": 1,
    "—th": 1,
    "rea": 1,
    " 9t": 1,
    "—in": 1,
    "28 ": 1,
    " Oc": 1,
    "ean": 1,
    "e V": 1,
    "edr": 1,
    "a I": 1,
    "nn ": 2,
    "ub.": 1,
    " sc": 2,
    "ule": 1,
    "o h": 1,
    "der": 1,
    " Cu": 1,
    "hes": 1,
    " if": 1,
    " Wo": 1,
    "rld": 1,
    "r I": 1,
    "I h": 1,
    "ad ": 5,
    "ven": 2,
    "ed.": 2,
    "its": 1,
    "elf": 1,
    ", l": 1,
    "yin": 2,
    "g 1": 1,
    "57 ": 1,
    "yar": 1,
    "ds ": 5,
    "tee": 1,
    "dge": 1,
    "y p": 1,
    "alm": 1,
    " tr": 2,
    "ees": 1,
    "epp": 1,
    "rs;": 1,
    "ldo": 1,
    "m p": 1,
    "asy": 1,
    " du": 2,
    "o s": 2,
    "tif": 1,
    "f o": 1,
    "cea": 1,
    "n b": 2,
    "zes": 1,
    "Oce": 1,
    "s r": 3,
    "ede": 1,
    "t T": 1,
    "ren": 1,
    "t J": 1,
    "s S": 1,
    "r. ": 2,
    "7, ": 1,
    "y B": 1,
    "obb": 2,
    "y W": 1,
    "98.": 1,
    " Jo": 2,
    "nes": 4,
    "mpt": 2,
    "duc": 1,
    "f S": 2,
    "ng'": 4,
    "gn ": 2,
    "  A": 1,
    "t E": 1,
    " ap": 2,
    "ach": 2,
    "lls": 3,
    "cei": 1,
    "vab": 1,
    "le ": 4,
    "ang": 2,
    "var": 1,
    "ied": 3,
    " us": 2,
    "ava": 1,
    "ila": 1,
    "pog": 1,
    "rap": 2,
    "hy.": 1,
    "les": 1,
    "yed": 1,
    "rai": 1,
    "ght": 2,
    " up": 1,
    "ill": 2,
    "sin": 2,
    "lon": 1,
    "cre": 1,
    "sts": 1,
    "sec": 2,
    "ond": 2,
    " si": 1,
    "tes": 1,
    " pl": 2,
    "elo": 1,
    "w, ": 1,
    "m o": 2,
    "hil": 4,
    "nex": 1,
    "bro": 1,
    "t y": 1,
    "top": 3,
    "d s": 5,
    "lop": 1,
    "end": 2,
    "ogr": 2,
    "aph": 2,
    "y h": 2,
    "oul": 3,
    " ad": 1,
    "van": 1,
    "tag": 1,
    "f. ": 1,
    "His": 3,
    "ski": 1,
    "n m": 1,
    "pre": 1,
    "ve ": 2,
    "Fai": 1,
    "rmo": 1,
    "Le ": 1,
    "oir": 1,
    " Ri": 1,
    "che": 1,
    "u w": 1,
    "ged": 1,
    "ild": 2,
    "y s": 1,
    "pie": 1,
    "0 f": 1,
    " el": 1,
    "eva": 1,
    "n c": 1,
    "ge.": 1,
    "ews": 1,
    "pap": 1,
    "col": 1,
    "umn": 1,
    "d B": 1,
    "y J": 1,
    "iog": 1,
    " O.": 1,
    " B.": 1,
    " Ke": 1,
    "r w": 1,
    "rot": 1,
    "\"so": 1,
    "cel": 1,
    "len": 1,
    "uth": 1,
    "ori": 2,
    "ty ": 3,
    " ol": 1,
    "d m": 1,
    "Ame": 2,
    "ric": 2,
    "f, ": 1,
    " ra": 1,
    "r f": 1,
    "s [": 1,
    "b] ": 1,
    "oo ": 2,
    "If ": 1,
    "any": 3,
    "cis": 2,
    "it ": 1,
    "wou": 2,
    "lik": 1,
    "ely": 1,
    "n o": 1,
    "eir": 1,
    " ab": 1,
    "ili": 1,
    "rep": 1,
    "hot": 4,
    "goo": 2,
    "s i": 1,
    " wr": 1,
    "gle": 2,
    "fte": 2,
    "n i": 1,
    "nco": 1,
    "rpo": 1,
    "two": 2,
    "a c": 1,
    "row": 1,
    " ce": 1,
    "are": 2,
    "a, ": 2,
    "nne": 2,
    "f f": 2,
    "ow ": 1,
    "arc": 2,
    "hit": 3,
    "ect": 2,
    " Do": 1,
    "d R": 2,
    "oss": 1,
    "s; ": 1,
    "rif": 1,
    "ff ": 1,
    " ba": 2,
    "ns,": 1,
    "orp": 1,
    "ora": 1,
    "tin": 4,
    "g f": 1,
    "als": 1,
    "ts ": 2,
    "ago": 1,
    " no": 2,
    "t r": 1,
    "eac": 1,
    "hin": 2,
    "cen": 3,
    "l p": 1,
    "eau": 1,
    "n. ": 1,
    "Mos": 1,
    "t p": 3,
    " wo": 2,
    "od-": 1,
    "d c": 1,
    "s—s": 1,
    "ggl": 1,
    "h t": 1,
    "bol": 2,
    "dne": 1,
    "ss,": 1,
    "igi": 1,
    "ity": 3,
    "ggr": 1,
    "ive": 3,
    "ura": 1,
    "l F": 1,
    "t L": 1,
    "e M": 1,
    "ano": 1,
    "ir ": 1,
    "Ric": 1,
    "ieu": 1,
    "n Q": 1,
    "ueb": 1,
    "ec,": 1,
    "nad": 1,
    "asc": 1,
    "g h": 1,
    "mel": 1,
    "ope": 2,
    "rty": 1,
    "pos": 1,
    "ses": 1,
    "bil": 2,
    "d h": 6,
    "n l": 1,
    "med": 1,
    "r t": 3,
    " gu": 1,
    " ve": 1,
    "sm ": 1,
    "but": 1,
    " cl": 1,
    " mo": 1,
    "tho": 2,
    "rov": 1,
    "oki": 1,
    "mos": 1,
    "r a": 2,
    "ct'": 1,
    "slo": 1,
    "pes": 1,
    "env": 1,
    "isi": 1,
    "bui": 1,
    "lt ": 1,
    "f a": 1,
    "3 U": 1,
    ".S.": 2,
    "9th": 1,
    " U.": 2,
    "S. ": 2,
    "d 1": 1,
    "8–2": 1,
    "0 S": 2,
    "e C": 2,
    "try": 1,
    "okl": 1,
    ", M": 1,
    "use": 1,
    "bur": 1,
    "b s": 1,
    "hwe": 1,
    "Bos": 1,
    " Fr": 2,
    "Oui": 1,
    "ge ": 3,
    "20,": 1,
    "y U": 1,
    "off": 1,
    ", f": 1,
    "ahe": 1,
    "Bri": 1,
    "tis": 1,
    "h s": 1,
    "tar": 1,
    "arr": 1,
    "y V": 1,
    " Te": 1,
    "ay.": 1,
    "nte": 1,
    "nti": 1,
    " af": 2,
    "o r": 2,
    "e \"": 2,
    "Abe": 1,
    "rde": 1,
    "Jou": 1,
    "rna": 3,
    "l\" ": 1,
    "h c": 1,
    "add": 1,
    "ie\"": 1,
    "cle": 1,
    "Ind": 1,
    "ian": 1,
    "apo": 1,
    "ar\"": 1,
    ", p": 1,
    "ubl": 1,
    "Sep": 1,
    "tem": 1,
    "13,": 1,
    "s \"": 1,
    "a d": 2,
    "ark": 1,
    "agn": 1,
    "itu": 1,
    "de\"": 1,
    "urp": 1,
    "ris": 1,
    "wel": 1,
    "l i": 1,
    "n r": 2,
    "wo,": 1,
    "ayi": 1,
    "alo": 1,
    "ner": 1,
    "g o": 1,
    "ffi": 1,
    "cia": 1,
    "cco": 1,
    "mpa": 1,
    "nie": 1,
    "gam": 1,
    "ste": 5,
    "rfu": 1,
    "roa": 1,
    "akn": 1,
    "ime": 2,
    " er": 1,
    "ic ": 1,
    "put": 1,
    "g. ": 1,
    "Des": 1,
    "pit": 1,
    "sma": 1,
    "ll ": 1,
    "phy": 1,
    "siq": 1,
    "ue—": 1,
    "wei": 1,
    "ghe": 1,
    " 12": 1,
    "0 p": 1,
    "ds—": 1,
    "scr": 1,
    "ibe": 1,
    " lo": 1,
    "e b": 1,
    "all": 1,
    "nsi": 1,
    "s s": 2,
    "ot ": 1,
    "p. ": 1,
    "Thu": 1,
    "rsd": 1,
    "wo ": 2,
    "ida": 1,
    "esu": 1,
    "lts": 1,
    "h R": 1,
    "ay,": 1,
    "Var": 1,
    "don": 1,
    ", w": 1,
    "ho ": 1,
    "sto": 1,
    "od ": 1,
    "ema": 2,
    "rka": 1,
    "r i": 1,
    "adi": 1,
    "cul": 1,
    "ar ": 1,
    "bri": 1,
    "lli": 1,
    "hod": 1,
    "him": 1,
    "sel": 1,
    "f i": 1,
    "bea": 1,
    "r F": 1,
    "ran": 1,
    " Ou": 1,
    "2 a": 1,
    "4. ": 1,
    "A d": 1,
    "isa": 1,
    "ppo": 1,
    "ird": 1,
    " 82": 1,
    "owe": 1,
    ", r": 2,
    "uin": 1,
    "d e": 1,
    "tua": 1,
    "h o": 1,
    "n 3": 1,
    "10,": 1,
    " +1": 1,
    "8 t": 1,
    "o p": 1,
    "ar,": 1,
    " ni": 1,
    "nth": 1,
    "h. ": 1,
    "won": 1,
    " $4": 1,
    "\"No": 1,
    "te:": 1,
    "g n": 1,
    "Tou": 1,
    "p.\"": 1,
    " NT": 1,
    " = ": 2,
    "No ": 1,
    "t<b": 2,
    "r> ": 3,
    "DNP": 1,
    "Did": 1,
    "<br": 1,
    "> C": 1,
    "UT ": 1,
    "= M": 1,
    "lf-": 1,
    " cu": 1,
    "\"T\"": 1,
    "dic": 1,
    "e<b": 1,
    "Yel": 1,
    "ckg": 1,
    "p-1": 1,
    "ce:": 1,
    "fat": 1,
    "fiv": 1,
    "dre": 2,
    "thr": 1,
    "ee ": 1,
    "wif": 1,
    "lar": 1,
    "a M": 1,
    "aud": 1,
    "e O": 1,
    "y (": 1,
    "1–1": 1,
    "): ": 1,
    "Aft": 1,
    "ivo": 1,
    "rce": 1,
    "—an": 1,
    "dea": 1,
    "s c": 1,
    "n—h": 1,
    "2 t": 1,
    "o A": 1,
    "Car": 1,
    "oly": 1,
    "n J": 1,
    "ord": 1,
    "(19": 1,
    "22–": 1,
    "4),": 1,
    "wom": 1,
    "42 ": 1,
    " ju": 1,
    "nio": 1,
    "fe,": 1,
    "ara": 1,
    "etu": 1,
    "rne": 1,
    "rvi": 1,
    "vin": 1,
    "o l": 1,
    " En": 1,
    "gla": 1,
    "mar": 1,
    "ria": 1,
    "Ann": 1,
    "rda": 1,
    "n y": 1,
    "iel": 1,
    "dau": 1,
    "er:": 1,
    "die": 1,
    "64 ": 1,
    "tta": 1,
    "For": 1,
    " Fl": 1,
    "da,": 1,
    "mem": 1,
    "rol": 1,
    "ifi": 1,
    "c g": 1,
    "ct ": 1,
    " ea": 1,
    " 20": 1,
    "nev": 1,
    "cit": 1,
    "ip;": 1,
    "sus": 1,
    " li": 1,
    "a r": 1,
    "den": 1,
    "te.": 1
  },
  "qualityClass": 6
}
